capparselib/__init__.py
capparselib/cap_mappings.py
capparselib/parsers.py
capparselib/requirements-base.txt
capparselib/schema/CAP-v1.1.xsd
capparselib/schema/CAP-v1.2.xsd
capparselib/schema/atom.xsd
capparselib/schema/atom_test.xsd
capparselib/schema/cap10.xsd
capparselib/schema/cap10_extended.xsd
capparselib/schema/cap11.xsd
capparselib/schema/cap11_b.xsd
capparselib/schema/cap11_extended.xsd
capparselib/schema/cap12.xsd
capparselib/schema/cap12_extended.xsd
capparselib/schema/capv1.2-ipaws-profile-v1.0-pr02.xsd
capparselib/schema/dc.xsd
capparselib/schema/edxl-de.xsd
capparselib/schema/nws.xsd
capparselib/schema/nws2.xsd
capparselib/schema/rss-2_0.xsd
capparselib/schema/xml.xsd
capparselib-0.6.7.dist-info/LICENSE
capparselib-0.6.7.dist-info/METADATA
capparselib-0.6.7.dist-info/WHEEL
capparselib-0.6.7.dist-info/top_level.txt
capparselib-0.6.7.dist-info/RECORD
